.gitignore
HACKING.rst
INSTALL
LICENSE.MIT
MANIFEST.in
NEWS.rst
README
README.rst
SMOP.rst
setup.py
smop/__init__.py
smop/backend.py
smop/callgraph.py
smop/core.py
smop/fastsolver.py
smop/graphviz.py
smop/lexer.py
smop/liboctave.py
smop/main.py
smop/mybench.py
smop/node.py
smop/options.py
smop/parse.py
smop/parsetab.py
smop/r8_random.py
smop/recipes.py
smop/resolve.py
smop/solver.py
smop/sparsearray.py
smop/test_core.py
smop/test_lexer.py
smop/test_matlabarray.py
smop/test_parse.py
smop/test_primes.py
smop/test_runtime.py
smop/test_solver.py
smop/test_sparsearray.py
smop/version.py
smop.egg-info/PKG-INFO
smop.egg-info/SOURCES.txt
smop.egg-info/dependency_links.txt
smop.egg-info/entry_points.txt
smop.egg-info/requires.txt
smop.egg-info/top_level.txt